numintegrator/__init__.py
numintegrator/__main__.py
numintegrator/_integrators(old).py
numintegrator/helpers.py
numintegrator/integrators.py
numintegrator-0.0.0.dist-info/LICENSE
numintegrator-0.0.0.dist-info/METADATA
numintegrator-0.0.0.dist-info/WHEEL
numintegrator-0.0.0.dist-info/top_level.txt
numintegrator-0.0.0.dist-info/RECORD
